django_project_backup/__init__.py
django_project_backup/apps.py
django_project_backup/settings.py
django_project_backup/signals.py
django_project_backup/management/__init__.py
django_project_backup/management/commands/__init__.py
django_project_backup/management/commands/dpb_couchdb_dumpdata.py
django_project_backup/management/commands/dpb_couchdb_loaddata.py
django_project_backup/management/commands/dpb_filesystem_assets_backup.py
django_project_backup/management/commands/dpb_filesystem_dumpdata.py
django_project_backup/utils/__init__.py
django_project_backup/utils/commons.py
django_project_backup/utils/couchdb/__init__.py
django_project_backup/utils/couchdb/adapter.py
django_project_backup/utils/couchdb/serializers.py
django_project_backup/utils/couchdb/stream.py
django_project_backup/utils/filesystem/__init__.py
django_project_backup-0.1.8.dist-info/AUTHORS.rst
django_project_backup-0.1.8.dist-info/LICENSE.txt
django_project_backup-0.1.8.dist-info/METADATA
django_project_backup-0.1.8.dist-info/WHEEL
django_project_backup-0.1.8.dist-info/top_level.txt
django_project_backup-0.1.8.dist-info/RECORD
