Metadata-Version: 2.1
Name: django-project-backup
Version: 0.1.8
Summary: Add a short description here!
Home-page: https://github.com/pyscaffold/pyscaffold/
Author: pai
Author-email: paiuolo@gmail.com
License: mit
Project-URL: Documentation, https://pyscaffold.org/
Platform: any
Classifier: Development Status :: 4 - Beta
Classifier: Programming Language :: Python
License-File: LICENSE.txt
License-File: AUTHORS.rst
Requires-Dist: django
Requires-Dist: django-dotenv
Requires-Dist: ijson
Provides-Extra: testing
Requires-Dist: pytest ; extra == 'testing'
Requires-Dist: pytest-cov ; extra == 'testing'
